{
  "sliding-panes-obsidian:toggle-sliding-panes": [
    {
      "modifiers": [
        "Mod"
      ],
      "key": "T"
    }
  ],
  "hotkeysplus-obsidian:clear-current-line": [
    {
      "modifiers": [
        "Mod",
        "Shift"
      ],
      "key": "C"
    }
  ],
  "url-into-selection:paste-url-into-selection": [
    {
      "modifiers": [
        "Mod",
        "Shift"
      ],
      "key": "K"
    }
  ],
  "workspace:close-others": [
    {
      "modifiers": [
        "Mod",
        "Shift"
      ],
      "key": "W"
    }
  ],
  "insert-template": [
    {
      "modifiers": [
        "Mod",
        "Shift"
      ],
      "key": "I"
    }
  ]
}